setup.cfg
setup.py
cielo/__init__.py
cielo/api30/__init__.py
cielo/api30/address.py
cielo/api30/cieloEcommerce.py
cielo/api30/creditCard.py
cielo/api30/customer.py
cielo/api30/environment.py
cielo/api30/merchant.py
cielo/api30/objectJSON.py
cielo/api30/payment.py
cielo/api30/recurrentPayment.py
cielo/api30/sale.py
cielo/api30/request/__init__.py
cielo/api30/request/base.py
cielo/api30/request/createCardToken.py
cielo/api30/request/createSale.py
cielo/api30/request/deactivateRecorrency.py
cielo/api30/request/queryRecorrency.py
cielo/api30/request/querySale.py
cielo/api30/request/reactivateRecorrency.py
cielo/api30/request/updateSale.py
cieloApi3.egg-info/PKG-INFO
cieloApi3.egg-info/SOURCES.txt
cieloApi3.egg-info/dependency_links.txt
cieloApi3.egg-info/requires.txt
cieloApi3.egg-info/top_level.txt